setup.py
koality_cli/__init__.py
koality_cli/config_creator.py
koality_cli.egg-info/PKG-INFO
koality_cli.egg-info/SOURCES.txt
koality_cli.egg-info/dependency_links.txt
koality_cli.egg-info/entry_points.txt
koality_cli.egg-info/requires.txt
koality_cli.egg-info/top_level.txt
koality_cli/generators/__init__.py
koality_cli/generators/comment_generator.py
koality_cli/generators/config_generators.py
koality_cli/generators/section_generators/__init__.py
koality_cli/generators/section_generators/section_generators.py
koality_cli/generators/section_generators/java/__init__.py
koality_cli/generators/section_generators/java/compile_scripts_generator.py
koality_cli/generators/section_generators/java/package_generator.py
koality_cli/generators/section_generators/java/test_factory_generator.py
koality_cli/generators/section_generators/javascript/__init__.py
koality_cli/generators/section_generators/javascript/compile_scripts_generator.py
koality_cli/generators/section_generators/javascript/package_generator.py
koality_cli/generators/section_generators/javascript/test_factory_generator.py
koality_cli/generators/section_generators/nodejs/__init__.py
koality_cli/generators/section_generators/nodejs/compile_scripts_generator.py
koality_cli/generators/section_generators/nodejs/package_generator.py
koality_cli/generators/section_generators/nodejs/test_factory_generator.py
koality_cli/generators/section_generators/python/__init__.py
koality_cli/generators/section_generators/python/compile_scripts_generator.py
koality_cli/generators/section_generators/python/package_generator.py
koality_cli/generators/section_generators/python/test_factory_generator.py
koality_cli/generators/section_generators/ruby/__init__.py
koality_cli/generators/section_generators/ruby/compile_scripts_generator.py
koality_cli/generators/section_generators/ruby/package_generator.py
koality_cli/generators/section_generators/ruby/test_factory_generator.py
koality_cli/repo_reflector/__init__.py
koality_cli/repo_reflector/database_reflector.py
koality_cli/repo_reflector/dependency_reflector.py
koality_cli/repo_reflector/language_reflector.py
koality_cli/repo_reflector/reflector.py
koality_cli/scripts/__init__.py
