Metadata-Version: 1.0
Name: koality-cli
Version: 0.1.5
Summary: Koality client wrapper for git and hg
Home-page: https://koalitycode.com
Author: jchu @ koality
Author-email: jchu@koalitycode.com
License: Koality license and tos @ https://koalitycode.com/terms
Keywords: cli,command line
Platform: UNKNOWN
